unrar_cffi-0.2.2.dist-info/top_level.txt
unrar_cffi-0.2.2.dist-info/RECORD
unrar_cffi-0.2.2.dist-info/METADATA
unrar_cffi-0.2.2.dist-info/LICENSE
unrar_cffi-0.2.2.dist-info/WHEEL
unrar/cffi/_unrarlib.abi3.so
unrar/cffi/rarfile.py
unrar/cffi/unrarlib_py.h
unrar/cffi/unrarlib.py
unrar/cffi/unrarlib_ext.c
unrar/cffi/unrarlib_ext.h
