Metadata-Version: 2.1
Name: unrar-cffi
Version: 0.2.2
Summary: Read RAR file from python -- cffi edition
Home-page: https://github.com/davide-romanini/unrar-cffi
Author: Davide Romanini
Author-email: davide.romanini@gmail.com
License: apache-2.0
Keywords: rar,unrar,archive,cffi
Platform: UNKNOWN
Classifier: Development Status :: 3 - Alpha
Classifier: Intended Audience :: Developers
Classifier: Topic :: Software Development :: Libraries
Classifier: License :: OSI Approved :: Apache Software License
Classifier: Programming Language :: Python :: 3
Classifier: Programming Language :: Python :: 3.4
Classifier: Programming Language :: Python :: 3.5
Classifier: Programming Language :: Python :: 3.6
Classifier: Programming Language :: Python :: 3.7
Requires-Python: >=3.4
License-File: LICENSE
Requires-Dist: cffi
